mitmproxy_wireguard-0.1.23.dist-info/METADATA
mitmproxy_wireguard-0.1.23.dist-info/WHEEL
mitmproxy_wireguard-0.1.23.dist-info/license_files/LICENSE
mitmproxy_wireguard/__init__.py
mitmproxy_wireguard/__init__.pyi
mitmproxy_wireguard/py.typed
mitmproxy_wireguard/mitmproxy_wireguard.abi3.so
mitmproxy_wireguard-0.1.23.dist-info/RECORD
