Metadata-Version: 2.1
Name: mitmproxy_wireguard
Version: 0.1.23
Classifier: Programming Language :: Rust
Classifier: Programming Language :: Python :: Implementation :: CPython
Classifier: Programming Language :: Python :: Implementation :: PyPy
Classifier: Programming Language :: Python :: 3 :: Only
Classifier: Programming Language :: Python :: 3.7
Classifier: Programming Language :: Python :: 3.8
Classifier: Programming Language :: Python :: 3.9
Classifier: Programming Language :: Python :: 3.10
Classifier: Programming Language :: Python :: 3.11
Classifier: Development Status :: 5 - Production/Stable
License-File: LICENSE
Summary: WireGuard interface for mitmproxy
Author: Fabio Valentini <decathorpe@gmail.com>, Maximilian Hils <cargo@maximilianhils.com>
Author-email: Fabio Valentini <decathorpe@gmail.com>, Maximilian Hils <cargo@maximilianhils.com>
License: MIT
Requires-Python: >=3.7
Project-URL: Source Code, https://github.com/decathorpe/mitmproxy_wireguard
